README.md
setup.py
xcover_expression_language.egg-info/PKG-INFO
xcover_expression_language.egg-info/SOURCES.txt
xcover_expression_language.egg-info/dependency_links.txt
xcover_expression_language.egg-info/requires.txt
xcover_expression_language.egg-info/top_level.txt
xcover_lang/__init__.py
xcover_lang/grammar.py
xcover_lang/transformers.py
xcover_lang/utils.py
xcover_lang/tests/__init__.py
xcover_lang/tests/test_data_structures.py
xcover_lang/tests/test_functions.py
xcover_lang/tests/test_operators.py