Metadata-Version: 1.0
Name: xcover-expression-language
Version: 0.0.2
Summary: A DSL that evaluates against Python API
Home-page: UNKNOWN
Author: UNKNOWN
Author-email: UNKNOWN
License: UNKNOWN
Keywords: expression,string expression,XCover
Platform: UNKNOWN
